topsis_Manik_101903077/TOPSIS.py
topsis_Manik_101903077/__init__.py
Topsis_Manik-0.0.0.dist-info/LICENSE
Topsis_Manik-0.0.0.dist-info/METADATA
Topsis_Manik-0.0.0.dist-info/WHEEL
Topsis_Manik-0.0.0.dist-info/top_level.txt
Topsis_Manik-0.0.0.dist-info/RECORD
